gupshup/__init__.py
gupshup/client.py
gupshup/exceptions.py
gupshup_python-0.1.1.dist-info/LICENSE.txt
gupshup_python-0.1.1.dist-info/METADATA
gupshup_python-0.1.1.dist-info/WHEEL
gupshup_python-0.1.1.dist-info/RECORD
